tools.py
TipsTestProject-1.0.1.dist-info/METADATA
TipsTestProject-1.0.1.dist-info/RECORD
TipsTestProject-1.0.1.dist-info/WHEEL
TipsTestProject-1.0.1.dist-info/top_level.txt
Tipstestlib/Tipslibone.py
Tipstestlib/__init__.py
Tipstestlib/testlib1.py
