Metadata-Version: 2.1
Name: TipsTestProject
Version: 1.0.1
Summary: this is a niubi lib
Home-page: http://github.com/
Author: Tips Lee
Author-email: tips@qq.com
License: MIT
Platform: UNKNOWN
